bmtk/__init__.py
bmtk/analyzer/__init__.py
bmtk/analyzer/cell_vars.py
bmtk/analyzer/compartment.py
bmtk/analyzer/ecp.py
bmtk/analyzer/edges.py
bmtk/analyzer/firing_rates.py
bmtk/analyzer/io_tools.py
bmtk/analyzer/spike_trains.py
bmtk/analyzer/spikes_analyzer.py
bmtk/analyzer/spikes_loader.py
bmtk/analyzer/utils.py
bmtk/builder/__init__.py
bmtk/builder/builder_utils.py
bmtk/builder/connection_map.py
bmtk/builder/connector.py
bmtk/builder/edge.py
bmtk/builder/functor_cache.py
bmtk/builder/id_generator.py
bmtk/builder/index_builders.py
bmtk/builder/iterator.py
bmtk/builder/network_builder.py
bmtk/builder/networks.py
bmtk/builder/node.py
bmtk/builder/node_pool.py
bmtk/builder/node_set.py
bmtk/builder/auxi/__init__.py
bmtk/builder/auxi/edge_connectors.py
bmtk/builder/auxi/node_params.py
bmtk/builder/bionet/__init__.py
bmtk/builder/bionet/swc_reader.py
bmtk/builder/edges_sorter/__init__.py
bmtk/builder/edges_sorter/memory_sorter.py
bmtk/builder/edges_sorter/merge_sorter.py
bmtk/builder/network_adaptors/__init__.py
bmtk/builder/network_adaptors/dm_network.py
bmtk/builder/network_adaptors/dm_network_orig.py
bmtk/builder/network_adaptors/edge_props_table.py
bmtk/builder/network_adaptors/edges_collator.py
bmtk/builder/network_adaptors/network.py
bmtk/builder/network_adaptors/nxnetwork.py
bmtk/simulator/__init__.py
bmtk/simulator/bionet/README.md
bmtk/simulator/bionet/__init__.py
bmtk/simulator/bionet/biocell.py
bmtk/simulator/bionet/bionetwork.py
bmtk/simulator/bionet/biosimulator.py
bmtk/simulator/bionet/cell.py
bmtk/simulator/bionet/config.py
bmtk/simulator/bionet/gids.py
bmtk/simulator/bionet/iclamp.py
bmtk/simulator/bionet/import3d.hoc
bmtk/simulator/bionet/io_tools.py
bmtk/simulator/bionet/morphology.py
bmtk/simulator/bionet/nml_reader.py
bmtk/simulator/bionet/nrn.py
bmtk/simulator/bionet/pointprocesscell.py
bmtk/simulator/bionet/pointsomacell.py
bmtk/simulator/bionet/pyfunction_cache.py
bmtk/simulator/bionet/seclamp.py
bmtk/simulator/bionet/sonata_adaptors.py
bmtk-1.1.3.dist-info/licenses/LICENSE.txt
bmtk-1.1.3.dist-info/METADATA
bmtk-1.1.3.dist-info/WHEEL
bmtk-1.1.3.dist-info/top_level.txt
bmtk-1.1.3.dist-info/RECORD
