Metadata-Version: 2.4
Name: bmtk
Version: 1.1.3
Summary: Brain Modeling Toolkit
Home-page: https://github.com/AllenInstitute/bmtk
Author: Kael Dai
Author-email: kaeld@alleninstitute.org
Keywords: neuroscience,scientific,modeling,simulation
Platform: any
Classifier: Development Status :: 5 - Production/Stable
Classifier: Intended Audience :: Science/Research
Classifier: License :: OSI Approved :: BSD License
Classifier: Natural Language :: English
Classifier: Operating System :: OS Independent
Classifier: Programming Language :: Python :: 2.7
Classifier: Programming Language :: Python :: 3.6
Classifier: Programming Language :: Python :: 3.7
Classifier: Programming Language :: Python :: 3.8
Classifier: Programming Language :: Python :: 3.9
Classifier: Topic :: Scientific/Engineering :: Bio-Informatics
License-File: LICENSE.txt
Requires-Dist: jsonschema
Requires-Dist: pandas
Requires-Dist: numpy
Requires-Dist: six
Requires-Dist: h5py
Requires-Dist: matplotlib
Requires-Dist: enum; python_version <= "2.7"
Requires-Dist: scipy
Requires-Dist: scikit-image
Requires-Dist: sympy
Requires-Dist: pynrrd
Provides-Extra: bionet
Requires-Dist: NEURON; extra == "bionet"
Provides-Extra: mintnet
Requires-Dist: tensorflow; extra == "mintnet"
Provides-Extra: pointnet
Requires-Dist: NEST; extra == "pointnet"
Provides-Extra: popnet
Requires-Dist: DiPDE; extra == "popnet"
Dynamic: author
Dynamic: author-email
Dynamic: classifier
Dynamic: description
Dynamic: description-content-type
Dynamic: home-page
Dynamic: keywords
Dynamic: license-file
Dynamic: platform
Dynamic: provides-extra
Dynamic: requires-dist
Dynamic: summary
